{
  "content": [
    {
      "id": 0,
      "code": "FULL_TIME",
      "nameEn": "Full-time",
      "nameFr": "Temps plein",
      "effectiveDate": "1970-01-01T00:00:00Z",
      "expiryDate": null,
      "createdBy": "system",
      "createdDate": "2025-08-10T16:35:18.07Z",
      "lastModifiedBy": "system",
      "lastModifiedDate": "2025-08-10T16:35:18.07Z"
    },
    {
      "id": 1,
      "code": "PART_TIME",
      "nameEn": "Part-time",
      "nameFr": "Temps partiel",
      "effectiveDate": "1970-01-01T00:00:00Z",
      "expiryDate": null,
      "createdBy": "system",
      "createdDate": "2025-08-10T16:35:18.07Z",
      "lastModifiedBy": "system",
      "lastModifiedDate": "2025-08-10T16:35:18.07Z"
    },
    {
      "id": 2,
      "code": "CASUAL",
      "nameEn": "Casual",
      "nameFr": "Occasionnel",
      "effectiveDate": "1970-01-01T00:00:00Z",
      "expiryDate": null,
      "createdBy": "system",
      "createdDate": "2025-08-10T16:35:18.07Z",
      "lastModifiedBy": "system",
      "lastModifiedDate": "2025-08-10T16:35:18.07Z"
    },
    {
      "id": 3,
      "code": "TERM",
      "nameEn": "Term",
      "nameFr": "Durée déterminée",
      "effectiveDate": "1970-01-01T00:00:00Z",
      "expiryDate": null,
      "createdBy": "system",
      "createdDate": "2025-08-10T16:35:18.07Z",
      "lastModifiedBy": "system",
      "lastModifiedDate": "2025-08-10T16:35:18.07Z"
    }
  ]
}
